pyhalboy/__init__.py
pyhalboy/navigator.py
pyhalboy/py.typed
pyhalboy/resource.py
pyhalboy/types.py
tobyclemson_pyhalboy-1.0.8.dist-info/LICENSE.md
tobyclemson_pyhalboy-1.0.8.dist-info/METADATA
tobyclemson_pyhalboy-1.0.8.dist-info/WHEEL
tobyclemson_pyhalboy-1.0.8.dist-info/RECORD
