Metadata-Version: 2.1
Name: tobyclemson.pyhalboy
Version: 1.0.8
Summary: Halboy port to python for everything HAL related.
License: MIT
Author: Bamdad Dashtban
Author-email: bamdadd@gmail.com
Requires-Python: >=3.13,<4.0
Classifier: License :: OSI Approved :: MIT License
Classifier: Programming Language :: Python :: 3
Requires-Dist: httpx (>=0.28.1,<0.29.0)
Requires-Dist: uritemplate (>=4.1.1,<5.0.0)
